Workbook

Sheet Income Statement
A1: ACCESS BANK PLC
A2: Consolidated Income Statement (NGN Millions)
A4: For the year ended 31 December | B4: 2018 | C4: 2019 | D4: 2020 | E4: 2021 | F4: 2022
A6: Interest Income (Effective Interest Rate) | B6: 360308 | C6: 453550 | D6: 425666 | E6: 519417 | F6: 769079
A7: Interest Income (FVTPL) | B7: 20607 | C7: 83297 | D7: 63551 | E7: 82234 | F7: 57506
A8: Interest Expense | B8: -207337 | C8: -259618 | D8: -226267 | E8: -300243 | F8: -467729
A9: Net Interest Income | B9: =SUM(B6:B8) -> 173578 | C9: =SUM(C6:C8) -> 277229 | D9: =SUM(D6:D8) -> 262950 | E9: =SUM(E6:E8) -> 301408 | F9: =SUM(F6:F8) -> 358856
A11: Net Impairment Charge | B11: -14657 | C11: -20189 | D11: -62893 | E11: -83214 | F11: -197790
A12: Net Interest Income After Impairment | B12: =B9+B11 -> 158921 | C12: =C9+C11 -> 257040 | D12: =D9+D11 -> 200057 | E12: =E9+E11 -> 218194 | F12: =F9+F11 -> 161066
A14: Fee and Commission Income | B14: 62096 | C14: 91845 | D14: 116700 | E14: 158917 | F14: 195470
A15: Fee and Commission Expense | B15: -9601 | C15: -17798 | D15: -23127 | E15: -40589 | F15: -51850
A16: Net Fee and Commission Income | B16: =B14+B15 -> 52495 | C16: =C14+C15 -> 74047 | D16: =D14+D15 -> 93573 | E16: =E14+E15 -> 118328 | F16: =F14+F15 -> 143620
A18: Net Gains on Financial Instruments | B18: 96324 | C18: 66102 | D18: 122690 | E18: 44780 | F18: 281304
A19: Net Foreign Exchange Gain/(Loss) | B19: -23769 | C19: -83876 | D19: -7568 | E19: 101101 | F19: 34500
A20: Net Gain/(Loss) on Fair Value Hedge | B20: 0 | C20: 0 | D20: -795 | E20: -872 | F20: 19742
A21: Other Operating Income | B21: 13179 | C21: 55836 | D21: 44474 | E21: 63411 | F21: 24660
A22: Bargain Purchase / Other Income | B22: 0 | C22: 0 | D22: 0 | E22: 2484 | F22: 0
A24: Total Operating Income | B24: =B12+B16+SUM(B18:B22) -> 297150 | C24: =C12+C16+SUM(C18:C22) -> 369149 | D24: =D12+D16+SUM(D18:D22) -> 452431 | E24: =E12+E16+SUM(E18:E22) -> 547426 | F24: =F12+F16+SUM(F18:F22) -> 664892
A26: Personnel Expenses | B26: -57144 | C26: -76964 | D26: -73173 | E26: -96613 | F26: -114763
A27: Depreciation | B27: -13535 | C27: -21233 | D27: -27615 | E27: -29139 | F27: -30298
A28: Amortization and Impairment | B28: -2799 | C28: -4475 | D28: -9913 | E28: -12974 | F28: -13825
A29: Other Operating Expenses | B29: -116149 | C29: -151098 | D29: -215807 | E29: -232213 | F29: -335720
A31: Total Operating Expenses | B31: =SUM(B26:B29) -> -189627 | C31: =SUM(C26:C29) -> -253770 | D31: =SUM(D26:D29) -> -326508 | E31: =SUM(E26:E29) -> -370939 | F31: =SUM(F26:F29) -> -494606
A33: Profit Before Tax | B33: =B24+B31 -> 107523 | C33: =C24+C31 -> 115379 | D33: =D24+D31 -> 125923 | E33: =E24+E31 -> 176487 | F33: =F24+F31 -> 170286
A34: Income Tax Expense | B34: -8207 | C34: -17869 | D34: -19912 | E34: -16485 | F34: -14529
A36: Profit for the Year | B36: =B33+B34 -> 99316 | C36: =C33+C34 -> 97510 | D36: =D33+D34 -> 106011 | E36: =E33+E34 -> 160002 | F36: =F33+F34 -> 155757

Sheet Balance Sheet
A1: ACCESS BANK PLC
A2: Consolidated Balance Sheet (NGN Millions)
A4: As at 31 December | B4: 2018 | C4: 2019 | D4: 2020 | E4: 2021 | F4: 2022
A6: ASSETS
A7: Cash and Balances with Banks | B7: 740926 | C7: 723064 | D7: 723873 | E7: 1487665 | F7: 1961100
A8: Investment Under Management | B8: 23839 | C8: 28292 | D8: 30451 | E8: 34942 | F8: 3742
A9: Non Pledged Trading Assets | B9: 38817 | C9: 129819 | D9: 207952 | E9: 892508 | F9: 102690
A10: Derivative Financial Assets | B10: 128440 | C10: 143521 | D10: 251113 | E10: 171332 | F10: 402497
A11: Loans and Advances to Banks | B11: 142490 | C11: 152825 | D11: 392821 | E11: 284548 | F11: 455710
A12: Loans and Advances to Customers | B12: 1993606 | C12: 2911580 | D12: 3218107 | E12: 4161364 | F12: 5100807
A13: Pledged Assets | B13: 554053 | C13: 605556 | D13: 228546 | E13: 344537 | F13: 1265279
A14: Investment Securities | B14: 501072 | C14: 1084604 | D14: 1749549 | E14: 2270338 | F14: 2761070
A15: Investment Properties | B15: 0 | C15: 927 | D15: 217 | E15: 217 | F15: 217
A16: Restricted Deposits and Other Assets | B16: 704327 | C16: 1055510 | D16: 1548891 | E16: 1707290 | F16: 2487691
A17: Investment in Associates | B17: 0 | C17: 0 | D17: 0 | E17: 2641 | F17: 7510
A18: Property and Equipment | B18: 103669 | C18: 211214 | D18: 226479 | E18: 247734 | F18: 293152
... A21: Assets Held for Sale | B21: 12242 | C21: 24958 | D21: 28318 | E21: 42737 | F21: 42039
A23: Total Assets | B23: =SUM(B7:B21) -> 4954157 | C23: =SUM(C7:C21) -> 7146611 | D23: =SUM(D7:D21) -> 8679747 | E23: =SUM(E7:E21) -> 11731966 | F23: =SUM(F7:F21) -> 14972309
A25: LIABILITIES
A26: Deposits from Financial Institutions | B26: 994573 | C26: 1186356 | D26: 958397 | E26: 1696521 | F26: 2005316
A27: Deposits from Customers | B27: 2564908 | C27: 4255837 | D27: 5587418 | E27: 6954827 | F27: 9251238
A28: Derivative Financial Liabilities | B28: 5206 | C28: 6886 | D28: 20881 | E28: 13953 | F28: 32737
A29: Current Tax Liabilities | B29: 4058 | C29: 3531 | D29: 2160 | E29: 4643 | F29: 4501
A30: Other Liabilities | B30: 246439 | C30: 324334 | D30: 379417 | E30: 560709 | F30: 753875
A31: Deferred Tax Liabilities | B31: 6457 | C31: 11273 | D31: 14877 | E31: 11652 | F31: 1796
A32: Debt Securities Issued | B32: 251251 | C32: 157988 | D32: 169160 | E32: 264495 | F32: 307253
A33: Interest-Bearing Borrowings | B33: 388417 | C33: 586603 | D33: 791455 | E33: 1171260 | F33: 1385424
A34: Retirement Benefit Obligation | B34: 2336 | C34: 3609 | D34: 4941 | E34: 3877 | F34: 3277
A36: Total Liabilities | B36: =SUM(B26:B34) -> 4463645 | C36: =SUM(C26:C34) -> 6536417 | D36: =SUM(D26:D34) -> 7928706 | E36: =SUM(E26:E34) -> 10681937 | F36: =SUM(F26:F34) -> 13745417
A38: EQUITY
A39: Share Capital and Premium | B39: 212439 | C39: 251811 | D39: 251811 | E39: 251811 | F39: 251811
A40: Additional Tier 1 Capital | B40: 0 | C40: 0 | D40: 0 | E40: 206355 | F40: 206355
A41: Retained Earnings | B41: 155593 | C41: 225119 | D41: 252397 | E41: 397273 | F41: 409653
A42: Other Reserves | B42: 114610 | C42: 129824 | D42: 246734 | E42: 194576 | F42: 344677
A43: Non-Controlling Interest | B43: 7870 | C43: 8529 | D43: 7339 | E43: 23477 | F43: 14395
A45: Total Equity | B45: =SUM(B39:B43) -> 490512 | C45: =SUM(C39:C43) -> 615283 | D45: =SUM(D39:D43) -> 758281 | E45: =SUM(E39:E43) -> 1073492 | F45: =SUM(F39:F43) -> 1226891
A47: Total Liabilities and Equity | B47: =B36+B45 -> 4954157 | C47: =C36+C45 -> 7151700 | D47: =D36+D45 -> 8686987 | E47: =E36+E45 -> 11755429 | F47: =F36+F45 -> 14972308
A49: Check (should be zero) | B49: =B23-B47 -> 0 | C49: =C23-C47 -> -5089 | D49: =D23-D47 -> -7240 | E49: =E23-E47 -> -23463 | F49: =F23-F47 -> 1

Sheet Cash Flow
A1: ACCESS BANK PLC
A2: Consolidated Cash Flow Statement (NGN Millions)
A4: For the year ended 31 December | B4: 2018 | C4: 2019 | D4: 2020 | E4: 2021 | F4: 2022
A6: OPERATING ACTIVITIES
A7: Profit Before Tax | B7: ='Income Statement'!B33 -> 107523 | C7: ='Income Statement'!C33 -> 115379 | D7: ='Income Statement'!D33 -> 125923 | E7: ='Income Statement'!E33 -> 176487 | F7: ='Income Statement'!F33 -> 170286
A8: Adjustments for Non-Cash Items | B8: 69382 | C8: 43934 | D8: 90636 | E8: 104495 | F8: 241186
A9: Changes in Working Capital | B9: 443802 | C9: 369447 | D9: -461527 | E9: 127412 | F9: 350111
A10: Net Cash from Operating Activities | B10: =SUM(B7:B9) -> 620707 | C10: =SUM(C7:C9) -> 528760 | D10: =SUM(D7:D9) -> -244968 | E10: =SUM(E7:E9) -> 408394 | F10: =SUM(F7:F9) -> 761583
A12: INVESTING ACTIVITIES
A13: Purchase of Investment Securities | B13: -1555682 | C13: -6043120 | D13: -8516797 | E13: -2219566 | F13: -1981681
A14: Proceeds from Investment Securities | B14: 1357276 | C14: 5661346 | D14: 8226359 | E14: 2220941 | F14: 1468478
A15: Capital Expenditure | B15: -24108 | C15: -45299 | D15: -43287 | E15: -49868 | F15: -93677
A16: Other Investing Activities | B16: 105201 | C16: 11203 | D16: 18705 | E16: 128254 | F16: 28446
A17: Net Cash from Investing Activities | B17: =SUM(B13:B16) -> -117313 | C17: =SUM(C13:C16) -> -415870 | D17: =SUM(D13:D16) -> -315020 | E17: =SUM(E13:E16) -> 79761 | F17: =SUM(F13:F16) -> -578434
A19: FINANCING ACTIVITIES
A20: Proceeds from Borrowings | B20: 123146 | C20: 103231 | D20: 256016 | E20: 429362 | F20: 678377
A21: Repayment of Borrowings | B21: -237494 | C21: -216208 | D21: -75582 | E21: -114479 | F21: -509479
A22: AT1 Capital Issued (net) | B22: 0 | C22: 0 | D22: 203748 | E22: 0 | F22: 0
A23: Dividends Paid | B23: -18803 | C23: -17773 | D23: -23104 | E23: -30213 | F23: -35810
A24: Other Financing Activities | B24: -27841 | C24: -2270 | D24: -248238 | E24: 224333 | F24: -98354
A25: Net Cash from Financing Activities | B25: =SUM(B20:B24) -> -160992 | C25: =SUM(C20:C24) -> -133020 | D25: =SUM(D20:D24) -> 112840 | E25: =SUM(E20:E24) -> 509003 | F25: =SUM(F20:F24) -> 34734
A27: Net Increase/(Decrease) in Cash | B27: =B10+B17+B25 -> 342402 | C27: =C10+C17+C25 -> -20130 | D27: =D10+D17+D25 -> -447148 | E27: =E10+E17+E25 -> 997158 | F27: =F10+F17+F25 -> 217883
A28: Cash at Beginning of Period | B28: 493424 | C28: 864565 | D28: 1226031 | E28: 837847 | F28: 1528923
A29: Effect of Exchange Rate Changes | B29: -2875 | C29: 7236 | D29: 39578 | E29: 33933 | F29: 52975
A30: Cash at End of Period | B30: =B28+B27+B29 -> 832951 | C30: =C28+C27+C29 -> 851671 | D30: =D28+D27+D29 -> 818461 | E30: =E28+E27+E29 -> 1868938 | F30: =F28+F27+F29 -> 1799781
A32: Check: Cash per Balance Sheet | B32: ='Balance Sheet'!B7 -> 740926 | C32: ='Balance Sheet'!C7 -> 723064 | D32: ='Balance Sheet'!D7 -> 723873 | E32: ='Balance Sheet'!E7 -> 1487665 | F32: ='Balance Sheet'!F7 -> 1961100
A33: Difference (should be zero) | B33: =B30-B32 -> 92025 | C33: =C30-C32 -> 128607 | D33: =D30-D32 -> 94588 | E33: =E30-E32 -> 381273 | F33: =F30-F32 -> -161319

Sheet Detail1
A1: Details for Sum of 2018 - For the year ended 31 December: Total Operating Expenses
A3: For the year ended 31 December | B3: 2018 | C3: 2019 | D3: 2020 | E3: 2021 | F3: 2022
A4: Total Operating Expenses | B4: 189627 | C4: 253770 | D4: 326508 | E4: 370939 | F4: 494606

Sheet Sheet3
W17: Row Labels | X17: Sum of 2018 | Y17: Sum of 2019 | Z17: Sum of 2020 | AA17: Sum of 2021 | AB17: Sum of 2022
W18: Total Operating Expenses | X18: -189627 | Y18: -253770 | Z18: -326508 | AA18: -370939 | AB18: -494606
W19: Grand Total | X19: -189627 | Y19: -253770 | Z19: -326508 | AA19: -370939 | AB19: -494606

Sheet Financial Ratios
A1: ACCESS BANK PLC
A2: Financial Ratios and Metrics
A4: Ratio / Metric | B4: 2018 | C4: 2019 | D4: 2020 | E4: 2021 | F4: 2022
A6: PROFITABILITY RATIOS
A7: Return on Assets (ROA) | B7: ='Income Statement'!B36/'Balance Sheet'!B23 -> 0.020047003 | C7: ='Income Statement'!C36/'Balance Sheet'!C23 -> 0.013644229 | D7: ='Income Statement'!D36/'Balance Sheet'!D23 -> 0.012213605 | E7: ='Income Statement'!E36/'Balance Sheet'!E23 -> 0.013638123 | F7: ='Income Statement'!F36/'Balance Sheet'!F23 -> 0.010403005
A8: Return on Equity (ROE) | B8: ='Income Statement'!B36/'Balance Sheet'!B45 -> 0.20247415 | C8: ='Income Statement'!C36/'Balance Sheet'!C45 -> 0.15847992 | D8: ='Income Statement'!D36/'Balance Sheet'!D45 -> 0.13980437 | E8: ='Income Statement'!E36/'Balance Sheet'!E45 -> 0.14904815 | F8: ='Income Statement'!F36/'Balance Sheet'!F45 -> 0.1269526
A9: Net Interest Margin (NIM) | B9: ='Income Statement'!B9/'Balance Sheet'!B23 -> 0.035036839 | C9: ='Income Statement'!C9/'Balance Sheet'!C23 -> 0.038791673 | D9: ='Income Statement'!D9/'Balance Sheet'!D23 -> 0.030294662 | E9: ='Income Statement'!E9/'Balance Sheet'!E23 -> 0.025691176 | F9: ='Income Statement'!F9/'Balance Sheet'!F23 -> 0.02396798
A10: Cost-to-Income Ratio | B10: =-'Income Statement'!B31/'Income Statement'!B24 -> 0.63815245 | C10: =-'Income Statement'!C31/'Income Statement'!C24 -> 0.68744599 | D10: =-'Income Statement'!D31/'Income Statement'!D24 -> 0.72167469 | E10: =-'Income Statement'!E31/'Income Statement'!E24 -> 0.67760574 | F10: =-'Income Statement'!F31/'Income Statement'!F24 -> 0.74388923
A11: Tax Rate | B11: =-'Income Statement'!B34/'Income Statement'!B33 -> 0.076327855 | C11: =-'Income Statement'!C34/'Income Statement'!C33 -> 0.1548722 | D11: =-'Income Statement'!D34/'Income Statement'!D33 -> 0.15812838 | E11: =-'Income Statement'!E34/'Income Statement'!E33 -> 0.093406313 | F11: =-'Income Statement'!F34/'Income Statement'!F33 -> 0.085321166
A13: ASSET QUALITY RATIOS
A14: Impairment Charge to Loans | B14: =-'Income Statement'!B11/'Balance Sheet'!B12 -> 0.0073520044 | C14: =-'Income Statement'!C11/'Balance Sheet'!C12 -> 0.0069340358 | D14: =-'Income Statement'!D11/'Balance Sheet'!D12 -> 0.019543477 | E14: =-'Income Statement'!E11/'Balance Sheet'!E12 -> 0.019996809 | F14: =-'Income Statement'!F11/'Balance Sheet'!F12 -> 0.038776217
A15: Loans to Deposits Ratio | B15: ='Balance Sheet'!B12/'Balance Sheet'!B27 -> 0.77726219 | C15: ='Balance Sheet'!C12/'Balance Sheet'!C27 -> 0.68413804 | D15: ='Balance Sheet'!D12/'Balance Sheet'!D27 -> 0.57595601 | E15: ='Balance Sheet'!E12/'Balance Sheet'!E27 -> 0.59834184 | F15: ='Balance Sheet'!F12/'Balance Sheet'!F27 -> 0.5513648
A16: Loans to Total Assets | B16: ='Balance Sheet'!B12/'Balance Sheet'!B23 -> 0.40241074 | C16: ='Balance Sheet'!C12/'Balance Sheet'!C23 -> 0.40740709 | D16: ='Balance Sheet'!D12/'Balance Sheet'!D23 -> 0.37076046 | E16: ='Balance Sheet'!E12/'Balance Sheet'!E23 -> 0.35470304 | F16: ='Balance Sheet'!F12/'Balance Sheet'!F23 -> 0.34068272
A18: CAPITAL RATIOS
A19: Equity to Assets | B19: ='Balance Sheet'!B45/'Balance Sheet'!B23 -> 0.099010185 | C19: ='Balance Sheet'!C45/'Balance Sheet'!C23 -> 0.086094374 | D19: ='Balance Sheet'!D45/'Balance Sheet'!D23 -> 0.087362109 | E19: ='Balance Sheet'!E45/'Balance Sheet'!E23 -> 0.091501458 | F19: ='Balance Sheet'!F45/'Balance Sheet'!F23 -> 0.081944007
A20: Deposits to Assets | B20: ='Balance Sheet'!B27/'Balance Sheet'!B23 -> 0.51772845 | C20: ='Balance Sheet'!C27/'Balance Sheet'!C23 -> 0.59550422 | D20: ='Balance Sheet'!D27/'Balance Sheet'!D23 -> 0.64373051 | E20: ='Balance Sheet'!E27/'Balance Sheet'!E23 -> 0.59281002 | F20: ='Balance Sheet'!F27/'Balance Sheet'!F23 -> 0.61788987
A21: Debt to Equity | B21: =('Balance Sheet'!B32+'Balance Sheet'!B33)/'Balance Sheet'!B45 -> 1.3040823 | C21: =('Balance Sheet'!C32+'Balance Sheet'!C33)/'Balance Sheet'!C45 -> 1.2101602 | D21: =('Balance Sheet'!D32+'Balance Sheet'!D33)/'Balance Sheet'!D45 -> 1.2668325 | E21: =('Balance Sheet'!E32+'Balance Sheet'!E33)/'Balance Sheet'!E45 -> 1.3374622 | F21: =('Balance Sheet'!F32+'Balance Sheet'!F33)/'Balance Sheet'!F45 -> 1.3796474
A23: GROWTH METRICS (YoY)
A24: Asset Growth | B24: =('Balance Sheet'!C23-'Balance Sheet'!B23)/'Balance Sheet'!B23 -> 0.44254835 | C24: =('Balance Sheet'!C23-'Balance Sheet'!C23)/'Balance Sheet'!C23 -> 0 | D24: =('Balance Sheet'!C23-'Balance Sheet'!D23)/'Balance Sheet'!D23 -> -0.17663372 | E24: =('Balance Sheet'!C23-'Balance Sheet'!E23)/'Balance Sheet'!E23 -> -0.39084285 | F24: =('Balance Sheet'!C23-'Balance Sheet'!F23)/'Balance Sheet'!F23 -> -0.5226781
A25: Loan Growth | B25: =('Balance Sheet'!C12-'Balance Sheet'!B12)/'Balance Sheet'!B12 -> 0.46045909 | C25: =('Balance Sheet'!C12-'Balance Sheet'!C12)/'Balance Sheet'!C12 -> 0 | D25: =('Balance Sheet'!C12-'Balance Sheet'!D12)/'Balance Sheet'!D12 -> -0.095250717 | E25: =('Balance Sheet'!C12-'Balance Sheet'!E12)/'Balance Sheet'!E12 -> -0.30033037 | F25: =('Balance Sheet'!C12-'Balance Sheet'!F12)/'Balance Sheet'!F12 -> -0.42919228
A26: Deposit Growth | B26: =('Balance Sheet'!C27-'Balance Sheet'!B27)/'Balance Sheet'!B27 -> 0.65925522 | C26: =('Balance Sheet'!C27-'Balance Sheet'!C27)/'Balance Sheet'!C27 -> 0 | D26: =('Balance Sheet'!C27-'Balance Sheet'!D27)/'Balance Sheet'!D27 -> -0.23831777 | E26: =('Balance Sheet'!C27-'Balance Sheet'!E27)/'Balance Sheet'!E27 -> -0.38807435 | F26: =('Balance Sheet'!C27-'Balance Sheet'!F27)/'Balance Sheet'!F27 -> -0.53997108
A27: Profit Growth | B27: =('Income Statement'!C36-'Income Statement'!B36)/'Income Statement'!B36 -> -0.018184381 | C27: =('Income Statement'!C36-'Income Statement'!C36)/'Income Statement'!C36 -> 0 | D27: =('Income Statement'!C36-'Income Statement'!D36)/'Income Statement'!D36 -> -0.080189792 | E27: =('Income Statement'!C36-'Income Statement'!E36)/'Income Statement'!E36 -> -0.39057012 | F27: =('Income Statement'!C36-'Income Statement'!F36)/'Income Statement'!F36 -> -0.37396072
A28: NII Growth | B28: =('Income Statement'!C9-'Income Statement'!B9)/'Income Statement'!B9 -> 0.59714365 | C28: =('Income Statement'!C9-'Income Statement'!C9)/'Income Statement'!C9 -> 0 | D28: =('Income Statement'!C9-'Income Statement'!D9)/'Income Statement'!D9 -> 0.054303099 | E28: =('Income Statement'!C9-'Income Statement'!E9)/'Income Statement'!E9 -> -0.080220167 | F28: =('Income Statement'!C9-'Income Statement'!F9)/'Income Statement'!F9 -> -0.2274645
A30: PER SHARE METRICS
A31: Shares Outstanding (millions) | B31: 32354 | C31: 35545 | D31: 35545 | E31: 35545 | F31: 35545
A32: Earnings Per Share (Kobo) | B32: ='Income Statement'!B36/B31*1000 -> 3069.6668 | C32: ='Income Statement'!C36/C31*1000 -> 2743.2832 | D32: ='Income Statement'!D36/D31*1000 -> 2982.4448 | E32: ='Income Statement'!E36/E31*1000 -> 4501.3926 | F32: ='Income Statement'!F36/F31*1000 -> 4381.9665
A33: Book Value Per Share (Kobo) | B33: ='Balance Sheet'!B45/B31*1000 -> 15160.784 | C33: ='Balance Sheet'!C45/C31*1000 -> 17309.973 | D33: ='Balance Sheet'!D45/D31*1000 -> 21332.986 | E33: ='Balance Sheet'!E45/E31*1000 -> 30200.928 | F33: ='Balance Sheet'!F45/F31*1000 -> 34516.556

Sheet Dashboard
J3: {=INDEX('Cash Flow'!B4:F4,1,MATCH(MAX('Cash Flow'!B7:F7),'Cash Flow'!B7:F7,O))} -> #NAME?

Sheet Sheet2
Q8: Column Labels
P9: Values | Q9: Debt to Equity | R9: Grand Total
P10: 2018% | Q10: 1.3040823 | R10: 1.3040823
P11: 2019% | Q11: 1.2101602 | R11: 1.2101602
P12: 2020% | Q12: 1.2668325 | R12: 1.2668325
P13: 2021% | Q13: 1.3374622 | R13: 1.3374622
P14: 2022% | Q14: 1.3796474 | R14: 1.3796474

Sheet Assumptions & Notes
A1: ACCESS BANK PLC
A2: Assumptions & Notes
A5: DATA SOURCE:
A6: All financial data extracted from Access Bank PLC Annual Reports (2018-2022)
A7: Source documents: Audited consolidated financial statements
A9: CURRENCY:
A10: All amounts in Nigerian Naira (NGN) Millions
A12: COLOR CODING:
A13: Blue text = Input values (hardcoded from financial statements)
A14: Black text = Calculated values (formulas)
A15: Green text = Links to other sheets
A17: REPORTING STANDARDS:
... A38: For questions or model updates, refer to source financial statements.
